hanzo_consensus/__init__.py
hanzo_consensus/consensus.py
hanzo_consensus/mcp_mesh.py
hanzo_consensus-0.1.0.dist-info/METADATA
hanzo_consensus-0.1.0.dist-info/WHEEL
hanzo_consensus-0.1.0.dist-info/RECORD
