Metadata-Version: 2.4
Name: hanzo-consensus
Version: 0.1.0
Summary: Metastable consensus protocol for multi-agent agreement
Project-URL: Homepage, https://github.com/hanzoai/python-sdk
Project-URL: Repository, https://github.com/hanzoai/python-sdk
Project-URL: Documentation, https://github.com/luxfi/consensus
Author-email: Hanzo AI <dev@hanzo.ai>
License-Expression: MIT
Keywords: consensus,distributed,metastable,multi-agent
Classifier: Development Status :: 4 - Beta
Classifier: Intended Audience :: Developers
Classifier: License :: OSI Approved :: MIT License
Classifier: Programming Language :: Python :: 3.11
Classifier: Programming Language :: Python :: 3.12
Requires-Python: >=3.11
